doublylist/__init__.py
doublylist/lib.py
doublylist/node.py
doublylist/node_list.py
doublylist/structure.py
doublylist-0.2.0.dist-info/METADATA
doublylist-0.2.0.dist-info/WHEEL
doublylist-0.2.0.dist-info/top_level.txt
doublylist-0.2.0.dist-info/RECORD
