Metadata-Version: 2.4
Name: doublylist
Version: 0.2.0
Summary: Python wrapper for a C doubly linked list implementation
Home-page: https://github.com/YourUsername/doublylist
Author: Erdal Nayir
Author-email: erdal.nayir2001@gmail.com
Classifier: Programming Language :: Python :: 3
Classifier: Operating System :: Microsoft :: Windows
Requires-Python: >=3.10
Dynamic: author
Dynamic: author-email
Dynamic: classifier
Dynamic: description
Dynamic: description-content-type
Dynamic: home-page
Dynamic: requires-python
Dynamic: summary
